<?xml version="1.0" encoding="utf-8" ?>
<Defs>

  <ThingDef ParentName="BaseBullet">
    <defName>AA_Bullet_Barb</defName>
    <label>barb</label>
		<thingClass>AnimalRangeAttack.AnimalProjectile</thingClass>

    <graphicData>
      <texPath>Things/Projectiles/AA_Barb</texPath>
      <graphicClass>Graphic_Single</graphicClass>
    </graphicData>
    <projectile>
      <flyOverhead>false</flyOverhead>
      <damageDef>AA_ToxicSting</damageDef>
      <damageAmountBase>5</damageAmountBase>
      <speed>64</speed>
    </projectile>
  </ThingDef>

  
  
</Defs>